scouter/__init__.py
scouter/_scouter.abi3.so
scouter/_scouter.pyi
scouter/alert/__init__.py
scouter/client/__init__.py
scouter/drift/__init__.py
scouter/evaluate/__init__.py
scouter/genai/__init__.py
scouter/genai/anthropic/__init__.py
scouter/genai/google/__init__.py
scouter/genai/openai/__init__.py
scouter/logging/__init__.py
scouter/mock/__init__.py
scouter/observe/__init__.py
scouter/profile/__init__.py
scouter/py.typed
scouter/queue/__init__.py
scouter/tracing/__init__.py
scouter/transport/__init__.py
scouter/types/__init__.py
scouter/util/__init__.py
scouter/version.py
scouter_ml-0.15.0.dist-info/METADATA
scouter_ml-0.15.0.dist-info/WHEEL
scouter_ml-0.15.0.dist-info/licenses/LICENSE
scouter_ml-0.15.0.dist-info/RECORD
