Metadata-Version: 2.4
Name: scouter-ml
Version: 0.15.0
Classifier: Programming Language :: Rust
Classifier: Programming Language :: Python :: Implementation :: CPython
Classifier: Programming Language :: Python :: Implementation :: PyPy
License-File: LICENSE
Summary: 
Author-email: Thorrester <<support@demmlai.com>>, russellkemmit <<support@demmlai.com>>
License-Expression: MIT
Requires-Python: >=3.10
